{
    "START": "Timestamp",
    "STOP": "Timestamp",
    "PATIENT": "string",
    "ENCOUNTER": "string",
    "CODE": "string",
    "SYSTEM": "string",
    "DESCRIPTION": "string",
    "TYPE": "string",
    "CATEGORY": "string",
    "REACTION1": "string",
    "DESCRIPTION1": "string",
    "SEVERITY1": "string",
    "REACTION2": "string",
    "DESCRIPTION2": "string",
    "SEVERITY2": "string",
    "Id": "string",
    "REASONCODE": "string",
    "REASONDESCRIPTION": "string",
    "PATIENTID": "string",
    "PROVIDERID": "string",
    "PRIMARYPATIENTINSURANCEID": "string",
    "SECONDARYPATIENTINSURANCEID": "string",
    "DEPARTMENTID": "string",
    "PATIENTDEPARTMENTID": "string",
    "DIAGNOSIS1": "string",
    "DIAGNOSIS2": "string",
    "DIAGNOSIS3": "string",
    "DIAGNOSIS4": "string",
    "DIAGNOSIS5": "string",
    "DIAGNOSIS6": "string",
    "DIAGNOSIS7": "string",
    "DIAGNOSIS8": "string",
    "REFERRINGPROVIDERID": "string",
    "APPOINTMENTID": "string",
    "CURRENTILLNESSDATE": "string",
    "SERVICEDATE": "Timestamp",
    "SUPERVISINGPROVIDERID": "string",
    "STATUS1": "string",
    "STATUS2": "string",
    "STATUSP": "string",
    "OUTSTANDING1": "numeric",
    "OUTSTANDING2": "numeric",
    "OUTSTANDINGP": "numeric",
    "LASTBILLEDDATE1": "Timestamp",
    "LASTBILLEDDATE2": "Timestamp",
    "LASTBILLEDDATEP": "Timestamp",
    "HEALTHCARECLAIMTYPEID1": "string",
    "HEALTHCARECLAIMTYPEID2": "string",
    "ID": "string",
    "CLAIMID": "string",
    "CHARGEID": "string",
    "AMOUNT": "numeric",
    "METHOD": "string",
    "FROMDATE": "Timestamp",
    "TODATE": "Timestamp",
    "PLACEOFSERVICE": "string",
    "PROCEDURECODE": "string",
    "MODIFIER1": "string",
    "MODIFIER2": "string",
    "DIAGNOSISREF1": "string",
    "DIAGNOSISREF2": "string",
    "DIAGNOSISREF3": "string",
    "DIAGNOSISREF4": "string",
    "UNITS": "numeric",
    "NOTES": "string",
    "UNITAMOUNT": "numeric",
    "TRANSFEROUTID": "string",
    "TRANSFERTYPE": "string",
    "PAYMENTS": "string",
    "ADJUSTMENTS": "string",
    "TRANSFERS": "string",
    "OUTSTANDING": "string",
    "LINENOTE": "string",
    "PATIENTINSURANCEID": "string",
    "FEESCHEDULEID": "string",
    "UDI": "string",
    "ORGANIZATION": "string",
    "PROVIDER": "string",
    "PAYER": "string",
    "ENCOUNTERCLASS": "string",
    "BASE_ENCOUNTER_COST": "numeric",
    "TOTAL_CLAIM_COST": "numeric",
    "PAYER_COVERAGE": "numeric",
    "DATE": "Timestamp",
    "SERIES_UID": "string",
    "BODYSITE_CODE": "string",
    "BODYSITE_DESCRIPTION": "string",
    "MODALITY_CODE": "string",
    "MODALITY_DESCRIPTION": "string",
    "INSTANCE_UID": "string",
    "SOP_CODE": "string",
    "SOP_DESCRIPTION": "string",
    "PROCEDURE_CODE": "string",
    "BASE_COST": "numeric",
    "DISPENSES": "int",
    "TOTALCOST": "inumericnt",
    "VALUE": "int",
    "NAME": "string",
    "ADDRESS": "string",
    "CITY": "string",
    "STATE": "string",
    "ZIP": "string",
    "LAT": "numeric",
    "LON": "numeric",
    "PHONE": "string",
    "REVENUE": "string",
    "UTILIZATION": "numeric",
    "BIRTHDATE": "Timestamp",
    "DEATHDATE": "Timestamp",
    "SSN": "string",
    "DRIVERS": "string",
    "PASSPORT": "string",
    "PREFIX": "string",
    "FIRST": "string",
    "LAST": "string",
    "SUFFIX": "string",
    "MAIDEN": "string",
    "MARITAL": "string",
    "RACE": "string",
    "ETHNICITY": "string",
    "GENDER": "string",
    "BIRTHPLACE": "string",
    "COUNTY": "string",
    "FIPS": "string",
    "HEALTHCARE_EXPENSES": "numeric",
    "HEALTHCARE_COVERAGE": "numeric",
    "INCOME": "numeric",
    "MEMBERID": "string",
    "START_DATE": "Timestamp",
    "END_DATE": "Timestamp",
    "SECONDARY_PAYER": "string",
    "PLAN_OWNERSHIP": "string",
    "OWNER_NAME": "string",
    "OWNERSHIP": "string",
    "STATE_HEADQUARTERED": "string",
    "AMOUNT_COVERED": "numeric",
    "AMOUNT_UNCOVERED": "numeric",
    "COVERED_ENCOUNTERS": "int",
    "UNCOVERED_ENCOUNTERS": "int",
    "COVERED_MEDICATIONS": "int",
    "UNCOVERED_MEDICATIONS": "int",
    "COVERED_PROCEDURES": "int",
    "UNCOVERED_PROCEDURES": "int",
    "COVERED_IMMUNIZATIONS": "int",
    "UNCOVERED_IMMUNIZATIONS": "int",
    "UNIQUE_CUSTOMERS": "string",
    "QOLS_AVG": "string",
    "MEMBER_MONTHS": "int",
    "SPECIALITY": "string",
    "ENCOUNTERS": "int",
    "PROCEDURES": "int",
    "QUANTITY": "int"
}